\doxysection{ljumptab.\+h}
\hypertarget{ljumptab_8h_source}{}\label{ljumptab_8h_source}\mbox{\hyperlink{ljumptab_8h}{Go to the documentation of this file.}}
\begin{DoxyCode}{0}
\DoxyCodeLine{00001\ \textcolor{comment}{/*}}
\DoxyCodeLine{00002\ \textcolor{comment}{**\ \$Id:\ ljumptab.h\ \$}}
\DoxyCodeLine{00003\ \textcolor{comment}{**\ Jump\ Table\ for\ the\ Lua\ interpreter}}
\DoxyCodeLine{00004\ \textcolor{comment}{**\ See\ Copyright\ Notice\ in\ lua.h}}
\DoxyCodeLine{00005\ \textcolor{comment}{*/}}
\DoxyCodeLine{00006\ }
\DoxyCodeLine{00007\ }
\DoxyCodeLine{00008\ \textcolor{preprocessor}{\#undef\ vmdispatch}}
\DoxyCodeLine{00009\ \textcolor{preprocessor}{\#undef\ vmcase}}
\DoxyCodeLine{00010\ \textcolor{preprocessor}{\#undef\ vmbreak}}
\DoxyCodeLine{00011\ }
\DoxyCodeLine{00012\ \textcolor{preprocessor}{\#define\ vmdispatch(x)\ \ \ \ \ goto\ *disptab[x];}}
\DoxyCodeLine{00013\ }
\DoxyCodeLine{00014\ \textcolor{preprocessor}{\#define\ vmcase(l)\ \ \ \ \ L\_\#\#l:}}
\DoxyCodeLine{00015\ }
\DoxyCodeLine{00016\ \textcolor{preprocessor}{\#define\ vmbreak\ \ \ \ \ vmfetch();\ vmdispatch(GET\_OPCODE(i));}}
\DoxyCodeLine{00017\ }
\DoxyCodeLine{00018\ }
\DoxyCodeLine{00019\ \textcolor{keyword}{static}\ \textcolor{keyword}{const}\ \textcolor{keywordtype}{void}\ *\textcolor{keyword}{const}\ disptab[\mbox{\hyperlink{lopcodes_8h_a1fb469ba81540d3314cfbe37c675ba20}{NUM\_OPCODES}}]\ =\ \{}
\DoxyCodeLine{00020\ }
\DoxyCodeLine{00021\ \textcolor{preprocessor}{\#if\ 0}}
\DoxyCodeLine{00022\ **\ you\ can\ update\ the\ following\ list\ with\ \textcolor{keyword}{this}\ command:}
\DoxyCodeLine{00023\ **}
\DoxyCodeLine{00024\ **\ \ sed\ -\/n\ \textcolor{stringliteral}{'/\string^OP\_/!d;\ s/OP\_/\(\backslash\)\&\(\backslash\)\&L\_OP\_/\ ;\ s/,.*/,/\ ;\ s/\(\backslash\)/.*//\ ;\ p'}\ \ lopcodes.h}
\DoxyCodeLine{00025\ **}
\DoxyCodeLine{00026\ \textcolor{preprocessor}{\#endif}}
\DoxyCodeLine{00027\ }
\DoxyCodeLine{00028\ \&\&L\_OP\_MOVE,}
\DoxyCodeLine{00029\ \&\&L\_OP\_LOADI,}
\DoxyCodeLine{00030\ \&\&L\_OP\_LOADF,}
\DoxyCodeLine{00031\ \&\&L\_OP\_LOADK,}
\DoxyCodeLine{00032\ \&\&L\_OP\_LOADKX,}
\DoxyCodeLine{00033\ \&\&L\_OP\_LOADFALSE,}
\DoxyCodeLine{00034\ \&\&L\_OP\_LFALSESKIP,}
\DoxyCodeLine{00035\ \&\&L\_OP\_LOADTRUE,}
\DoxyCodeLine{00036\ \&\&L\_OP\_LOADNIL,}
\DoxyCodeLine{00037\ \&\&L\_OP\_GETUPVAL,}
\DoxyCodeLine{00038\ \&\&L\_OP\_SETUPVAL,}
\DoxyCodeLine{00039\ \&\&L\_OP\_GETTABUP,}
\DoxyCodeLine{00040\ \&\&L\_OP\_GETTABLE,}
\DoxyCodeLine{00041\ \&\&L\_OP\_GETI,}
\DoxyCodeLine{00042\ \&\&L\_OP\_GETFIELD,}
\DoxyCodeLine{00043\ \&\&L\_OP\_SETTABUP,}
\DoxyCodeLine{00044\ \&\&L\_OP\_SETTABLE,}
\DoxyCodeLine{00045\ \&\&L\_OP\_SETI,}
\DoxyCodeLine{00046\ \&\&L\_OP\_SETFIELD,}
\DoxyCodeLine{00047\ \&\&L\_OP\_NEWTABLE,}
\DoxyCodeLine{00048\ \&\&L\_OP\_SELF,}
\DoxyCodeLine{00049\ \&\&L\_OP\_ADDI,}
\DoxyCodeLine{00050\ \&\&L\_OP\_ADDK,}
\DoxyCodeLine{00051\ \&\&L\_OP\_SUBK,}
\DoxyCodeLine{00052\ \&\&L\_OP\_MULK,}
\DoxyCodeLine{00053\ \&\&L\_OP\_MODK,}
\DoxyCodeLine{00054\ \&\&L\_OP\_POWK,}
\DoxyCodeLine{00055\ \&\&L\_OP\_DIVK,}
\DoxyCodeLine{00056\ \&\&L\_OP\_IDIVK,}
\DoxyCodeLine{00057\ \&\&L\_OP\_BANDK,}
\DoxyCodeLine{00058\ \&\&L\_OP\_BORK,}
\DoxyCodeLine{00059\ \&\&L\_OP\_BXORK,}
\DoxyCodeLine{00060\ \&\&L\_OP\_SHLI,}
\DoxyCodeLine{00061\ \&\&L\_OP\_SHRI,}
\DoxyCodeLine{00062\ \&\&L\_OP\_ADD,}
\DoxyCodeLine{00063\ \&\&L\_OP\_SUB,}
\DoxyCodeLine{00064\ \&\&L\_OP\_MUL,}
\DoxyCodeLine{00065\ \&\&L\_OP\_MOD,}
\DoxyCodeLine{00066\ \&\&L\_OP\_POW,}
\DoxyCodeLine{00067\ \&\&L\_OP\_DIV,}
\DoxyCodeLine{00068\ \&\&L\_OP\_IDIV,}
\DoxyCodeLine{00069\ \&\&L\_OP\_BAND,}
\DoxyCodeLine{00070\ \&\&L\_OP\_BOR,}
\DoxyCodeLine{00071\ \&\&L\_OP\_BXOR,}
\DoxyCodeLine{00072\ \&\&L\_OP\_SHL,}
\DoxyCodeLine{00073\ \&\&L\_OP\_SHR,}
\DoxyCodeLine{00074\ \&\&L\_OP\_MMBIN,}
\DoxyCodeLine{00075\ \&\&L\_OP\_MMBINI,}
\DoxyCodeLine{00076\ \&\&L\_OP\_MMBINK,}
\DoxyCodeLine{00077\ \&\&L\_OP\_UNM,}
\DoxyCodeLine{00078\ \&\&L\_OP\_BNOT,}
\DoxyCodeLine{00079\ \&\&L\_OP\_NOT,}
\DoxyCodeLine{00080\ \&\&L\_OP\_LEN,}
\DoxyCodeLine{00081\ \&\&L\_OP\_CONCAT,}
\DoxyCodeLine{00082\ \&\&L\_OP\_CLOSE,}
\DoxyCodeLine{00083\ \&\&L\_OP\_TBC,}
\DoxyCodeLine{00084\ \&\&L\_OP\_JMP,}
\DoxyCodeLine{00085\ \&\&L\_OP\_EQ,}
\DoxyCodeLine{00086\ \&\&L\_OP\_LT,}
\DoxyCodeLine{00087\ \&\&L\_OP\_LE,}
\DoxyCodeLine{00088\ \&\&L\_OP\_EQK,}
\DoxyCodeLine{00089\ \&\&L\_OP\_EQI,}
\DoxyCodeLine{00090\ \&\&L\_OP\_LTI,}
\DoxyCodeLine{00091\ \&\&L\_OP\_LEI,}
\DoxyCodeLine{00092\ \&\&L\_OP\_GTI,}
\DoxyCodeLine{00093\ \&\&L\_OP\_GEI,}
\DoxyCodeLine{00094\ \&\&L\_OP\_TEST,}
\DoxyCodeLine{00095\ \&\&L\_OP\_TESTSET,}
\DoxyCodeLine{00096\ \&\&L\_OP\_CALL,}
\DoxyCodeLine{00097\ \&\&L\_OP\_TAILCALL,}
\DoxyCodeLine{00098\ \&\&L\_OP\_RETURN,}
\DoxyCodeLine{00099\ \&\&L\_OP\_RETURN0,}
\DoxyCodeLine{00100\ \&\&L\_OP\_RETURN1,}
\DoxyCodeLine{00101\ \&\&L\_OP\_FORLOOP,}
\DoxyCodeLine{00102\ \&\&L\_OP\_FORPREP,}
\DoxyCodeLine{00103\ \&\&L\_OP\_TFORPREP,}
\DoxyCodeLine{00104\ \&\&L\_OP\_TFORCALL,}
\DoxyCodeLine{00105\ \&\&L\_OP\_TFORLOOP,}
\DoxyCodeLine{00106\ \&\&L\_OP\_SETLIST,}
\DoxyCodeLine{00107\ \&\&L\_OP\_CLOSURE,}
\DoxyCodeLine{00108\ \&\&L\_OP\_VARARG,}
\DoxyCodeLine{00109\ \&\&L\_OP\_GETVARG,}
\DoxyCodeLine{00110\ \&\&L\_OP\_ERRNNIL,}
\DoxyCodeLine{00111\ \&\&L\_OP\_VARARGPREP,}
\DoxyCodeLine{00112\ \&\&L\_OP\_EXTRAARG}
\DoxyCodeLine{00113\ }
\DoxyCodeLine{00114\ \};}

\end{DoxyCode}
