\doxysection{lopnames.\+h}
\hypertarget{lopnames_8h_source}{}\label{lopnames_8h_source}\mbox{\hyperlink{lopnames_8h}{Go to the documentation of this file.}}
\begin{DoxyCode}{0}
\DoxyCodeLine{00001\ \textcolor{comment}{/*}}
\DoxyCodeLine{00002\ \textcolor{comment}{**\ \$Id:\ lopnames.h\ \$}}
\DoxyCodeLine{00003\ \textcolor{comment}{**\ Opcode\ names}}
\DoxyCodeLine{00004\ \textcolor{comment}{**\ See\ Copyright\ Notice\ in\ lua.h}}
\DoxyCodeLine{00005\ \textcolor{comment}{*/}}
\DoxyCodeLine{00006\ }
\DoxyCodeLine{00007\ \textcolor{preprocessor}{\#if\ !defined(lopnames\_h)}}
\DoxyCodeLine{00008\ \textcolor{preprocessor}{\#define\ lopnames\_h}}
\DoxyCodeLine{00009\ }
\DoxyCodeLine{00010\ \textcolor{preprocessor}{\#include\ <stddef.h>}}
\DoxyCodeLine{00011\ }
\DoxyCodeLine{00012\ }
\DoxyCodeLine{00013\ \textcolor{comment}{/*\ ORDER\ OP\ */}}
\DoxyCodeLine{00014\ }
\DoxyCodeLine{00015\ \textcolor{keyword}{static}\ \textcolor{keyword}{const}\ \textcolor{keywordtype}{char}\ *\textcolor{keyword}{const}\ opnames[]\ =\ \{}
\DoxyCodeLine{00016\ \ \ \textcolor{stringliteral}{"{}MOVE"{}},}
\DoxyCodeLine{00017\ \ \ \textcolor{stringliteral}{"{}LOADI"{}},}
\DoxyCodeLine{00018\ \ \ \textcolor{stringliteral}{"{}LOADF"{}},}
\DoxyCodeLine{00019\ \ \ \textcolor{stringliteral}{"{}LOADK"{}},}
\DoxyCodeLine{00020\ \ \ \textcolor{stringliteral}{"{}LOADKX"{}},}
\DoxyCodeLine{00021\ \ \ \textcolor{stringliteral}{"{}LOADFALSE"{}},}
\DoxyCodeLine{00022\ \ \ \textcolor{stringliteral}{"{}LFALSESKIP"{}},}
\DoxyCodeLine{00023\ \ \ \textcolor{stringliteral}{"{}LOADTRUE"{}},}
\DoxyCodeLine{00024\ \ \ \textcolor{stringliteral}{"{}LOADNIL"{}},}
\DoxyCodeLine{00025\ \ \ \textcolor{stringliteral}{"{}GETUPVAL"{}},}
\DoxyCodeLine{00026\ \ \ \textcolor{stringliteral}{"{}SETUPVAL"{}},}
\DoxyCodeLine{00027\ \ \ \textcolor{stringliteral}{"{}GETTABUP"{}},}
\DoxyCodeLine{00028\ \ \ \textcolor{stringliteral}{"{}GETTABLE"{}},}
\DoxyCodeLine{00029\ \ \ \textcolor{stringliteral}{"{}GETI"{}},}
\DoxyCodeLine{00030\ \ \ \textcolor{stringliteral}{"{}GETFIELD"{}},}
\DoxyCodeLine{00031\ \ \ \textcolor{stringliteral}{"{}SETTABUP"{}},}
\DoxyCodeLine{00032\ \ \ \textcolor{stringliteral}{"{}SETTABLE"{}},}
\DoxyCodeLine{00033\ \ \ \textcolor{stringliteral}{"{}SETI"{}},}
\DoxyCodeLine{00034\ \ \ \textcolor{stringliteral}{"{}SETFIELD"{}},}
\DoxyCodeLine{00035\ \ \ \textcolor{stringliteral}{"{}NEWTABLE"{}},}
\DoxyCodeLine{00036\ \ \ \textcolor{stringliteral}{"{}SELF"{}},}
\DoxyCodeLine{00037\ \ \ \textcolor{stringliteral}{"{}ADDI"{}},}
\DoxyCodeLine{00038\ \ \ \textcolor{stringliteral}{"{}ADDK"{}},}
\DoxyCodeLine{00039\ \ \ \textcolor{stringliteral}{"{}SUBK"{}},}
\DoxyCodeLine{00040\ \ \ \textcolor{stringliteral}{"{}MULK"{}},}
\DoxyCodeLine{00041\ \ \ \textcolor{stringliteral}{"{}MODK"{}},}
\DoxyCodeLine{00042\ \ \ \textcolor{stringliteral}{"{}POWK"{}},}
\DoxyCodeLine{00043\ \ \ \textcolor{stringliteral}{"{}DIVK"{}},}
\DoxyCodeLine{00044\ \ \ \textcolor{stringliteral}{"{}IDIVK"{}},}
\DoxyCodeLine{00045\ \ \ \textcolor{stringliteral}{"{}BANDK"{}},}
\DoxyCodeLine{00046\ \ \ \textcolor{stringliteral}{"{}BORK"{}},}
\DoxyCodeLine{00047\ \ \ \textcolor{stringliteral}{"{}BXORK"{}},}
\DoxyCodeLine{00048\ \ \ \textcolor{stringliteral}{"{}SHLI"{}},}
\DoxyCodeLine{00049\ \ \ \textcolor{stringliteral}{"{}SHRI"{}},}
\DoxyCodeLine{00050\ \ \ \textcolor{stringliteral}{"{}ADD"{}},}
\DoxyCodeLine{00051\ \ \ \textcolor{stringliteral}{"{}SUB"{}},}
\DoxyCodeLine{00052\ \ \ \textcolor{stringliteral}{"{}MUL"{}},}
\DoxyCodeLine{00053\ \ \ \textcolor{stringliteral}{"{}MOD"{}},}
\DoxyCodeLine{00054\ \ \ \textcolor{stringliteral}{"{}POW"{}},}
\DoxyCodeLine{00055\ \ \ \textcolor{stringliteral}{"{}DIV"{}},}
\DoxyCodeLine{00056\ \ \ \textcolor{stringliteral}{"{}IDIV"{}},}
\DoxyCodeLine{00057\ \ \ \textcolor{stringliteral}{"{}BAND"{}},}
\DoxyCodeLine{00058\ \ \ \textcolor{stringliteral}{"{}BOR"{}},}
\DoxyCodeLine{00059\ \ \ \textcolor{stringliteral}{"{}BXOR"{}},}
\DoxyCodeLine{00060\ \ \ \textcolor{stringliteral}{"{}SHL"{}},}
\DoxyCodeLine{00061\ \ \ \textcolor{stringliteral}{"{}SHR"{}},}
\DoxyCodeLine{00062\ \ \ \textcolor{stringliteral}{"{}MMBIN"{}},}
\DoxyCodeLine{00063\ \ \ \textcolor{stringliteral}{"{}MMBINI"{}},}
\DoxyCodeLine{00064\ \ \ \textcolor{stringliteral}{"{}MMBINK"{}},}
\DoxyCodeLine{00065\ \ \ \textcolor{stringliteral}{"{}UNM"{}},}
\DoxyCodeLine{00066\ \ \ \textcolor{stringliteral}{"{}BNOT"{}},}
\DoxyCodeLine{00067\ \ \ \textcolor{stringliteral}{"{}NOT"{}},}
\DoxyCodeLine{00068\ \ \ \textcolor{stringliteral}{"{}LEN"{}},}
\DoxyCodeLine{00069\ \ \ \textcolor{stringliteral}{"{}CONCAT"{}},}
\DoxyCodeLine{00070\ \ \ \textcolor{stringliteral}{"{}CLOSE"{}},}
\DoxyCodeLine{00071\ \ \ \textcolor{stringliteral}{"{}TBC"{}},}
\DoxyCodeLine{00072\ \ \ \textcolor{stringliteral}{"{}JMP"{}},}
\DoxyCodeLine{00073\ \ \ \textcolor{stringliteral}{"{}EQ"{}},}
\DoxyCodeLine{00074\ \ \ \textcolor{stringliteral}{"{}LT"{}},}
\DoxyCodeLine{00075\ \ \ \textcolor{stringliteral}{"{}LE"{}},}
\DoxyCodeLine{00076\ \ \ \textcolor{stringliteral}{"{}EQK"{}},}
\DoxyCodeLine{00077\ \ \ \textcolor{stringliteral}{"{}EQI"{}},}
\DoxyCodeLine{00078\ \ \ \textcolor{stringliteral}{"{}LTI"{}},}
\DoxyCodeLine{00079\ \ \ \textcolor{stringliteral}{"{}LEI"{}},}
\DoxyCodeLine{00080\ \ \ \textcolor{stringliteral}{"{}GTI"{}},}
\DoxyCodeLine{00081\ \ \ \textcolor{stringliteral}{"{}GEI"{}},}
\DoxyCodeLine{00082\ \ \ \textcolor{stringliteral}{"{}TEST"{}},}
\DoxyCodeLine{00083\ \ \ \textcolor{stringliteral}{"{}TESTSET"{}},}
\DoxyCodeLine{00084\ \ \ \textcolor{stringliteral}{"{}CALL"{}},}
\DoxyCodeLine{00085\ \ \ \textcolor{stringliteral}{"{}TAILCALL"{}},}
\DoxyCodeLine{00086\ \ \ \textcolor{stringliteral}{"{}RETURN"{}},}
\DoxyCodeLine{00087\ \ \ \textcolor{stringliteral}{"{}RETURN0"{}},}
\DoxyCodeLine{00088\ \ \ \textcolor{stringliteral}{"{}RETURN1"{}},}
\DoxyCodeLine{00089\ \ \ \textcolor{stringliteral}{"{}FORLOOP"{}},}
\DoxyCodeLine{00090\ \ \ \textcolor{stringliteral}{"{}FORPREP"{}},}
\DoxyCodeLine{00091\ \ \ \textcolor{stringliteral}{"{}TFORPREP"{}},}
\DoxyCodeLine{00092\ \ \ \textcolor{stringliteral}{"{}TFORCALL"{}},}
\DoxyCodeLine{00093\ \ \ \textcolor{stringliteral}{"{}TFORLOOP"{}},}
\DoxyCodeLine{00094\ \ \ \textcolor{stringliteral}{"{}SETLIST"{}},}
\DoxyCodeLine{00095\ \ \ \textcolor{stringliteral}{"{}CLOSURE"{}},}
\DoxyCodeLine{00096\ \ \ \textcolor{stringliteral}{"{}VARARG"{}},}
\DoxyCodeLine{00097\ \ \ \textcolor{stringliteral}{"{}GETVARG"{}},}
\DoxyCodeLine{00098\ \ \ \textcolor{stringliteral}{"{}ERRNNIL"{}},}
\DoxyCodeLine{00099\ \ \ \textcolor{stringliteral}{"{}VARARGPREP"{}},}
\DoxyCodeLine{00100\ \ \ \textcolor{stringliteral}{"{}EXTRAARG"{}},}
\DoxyCodeLine{00101\ \ \ NULL}
\DoxyCodeLine{00102\ \};}
\DoxyCodeLine{00103\ }
\DoxyCodeLine{00104\ \textcolor{preprocessor}{\#endif}}
\DoxyCodeLine{00105\ }

\end{DoxyCode}
